LunPhpChangjianLoudong/README.md
LunPhpChangjianLoudong/__init__.py
LunPhpChangjianLoudong/__main__.py
LunPhpChangjianLoudong/file.epub
LunPhpChangjianLoudong/index.html
LunPhpChangjianLoudong/css/__init__.py
LunPhpChangjianLoudong/css/annotations.css
LunPhpChangjianLoudong/css/main.css
LunPhpChangjianLoudong/css/normalize.css
LunPhpChangjianLoudong/css/popup.css
LunPhpChangjianLoudong/font/__init__.py
LunPhpChangjianLoudong/font/fontello.eot
LunPhpChangjianLoudong/font/fontello.svg
LunPhpChangjianLoudong/font/fontello.ttf
LunPhpChangjianLoudong/font/fontello.woff
LunPhpChangjianLoudong/img/__init__.py
LunPhpChangjianLoudong/img/annotator-glyph-sprite.png
LunPhpChangjianLoudong/img/annotator-icon-sprite.png
LunPhpChangjianLoudong/img/apple-touch-icon.png
LunPhpChangjianLoudong/img/cancelfullscreen.png
LunPhpChangjianLoudong/img/close.png
LunPhpChangjianLoudong/img/fullscreen.png
LunPhpChangjianLoudong/img/loader.gif
LunPhpChangjianLoudong/img/menu-icon.png
LunPhpChangjianLoudong/img/save.png
LunPhpChangjianLoudong/img/saved.png
LunPhpChangjianLoudong/img/settings-s.png
LunPhpChangjianLoudong/img/settings.png
LunPhpChangjianLoudong/img/star.png
LunPhpChangjianLoudong/js/__init__.py
LunPhpChangjianLoudong/js/epub.js
LunPhpChangjianLoudong/js/epub.min.js
LunPhpChangjianLoudong/js/epub.min.map
LunPhpChangjianLoudong/js/hooks.min.js
LunPhpChangjianLoudong/js/hooks.min.map
LunPhpChangjianLoudong/js/reader.js
LunPhpChangjianLoudong/js/reader.js.map
LunPhpChangjianLoudong/js/reader.min.js
LunPhpChangjianLoudong/js/reader.min.map
LunPhpChangjianLoudong/js/hooks/__init__.py
LunPhpChangjianLoudong/js/hooks/extensions/__init__.py
LunPhpChangjianLoudong/js/hooks/extensions/highlight.js
LunPhpChangjianLoudong/js/libs/__init__.py
LunPhpChangjianLoudong/js/libs/jquery.min.js
LunPhpChangjianLoudong/js/libs/localforage.min.js
LunPhpChangjianLoudong/js/libs/screenfull.js
LunPhpChangjianLoudong/js/libs/screenfull.min.js
LunPhpChangjianLoudong/js/libs/zip.min.js
lun_php_changjian_loudong-2024.2.29.0.dist-info/METADATA
lun_php_changjian_loudong-2024.2.29.0.dist-info/WHEEL
lun_php_changjian_loudong-2024.2.29.0.dist-info/entry_points.txt
lun_php_changjian_loudong-2024.2.29.0.dist-info/top_level.txt
lun_php_changjian_loudong-2024.2.29.0.dist-info/RECORD
